{
    "frames": [
        {
            "duration": 0.10000000149011612,
            "h": 24,
            "w": 17,
            "x": 1,
            "y": 58
        },
        {
            "duration": 0.10000000149011612,
            "h": 23,
            "w": 17,
            "x": 20,
            "y": 57
        },
        {
            "duration": 0.10000000149011612,
            "h": 23,
            "w": 16,
            "x": 38,
            "y": 57
        },
        {
            "duration": 0.10000000149011612,
            "h": 24,
            "w": 16,
            "x": 55,
            "y": 56
        },
        {
            "duration": 0.10000000149011612,
            "h": 24,
            "w": 17,
            "x": 72,
            "y": 57
        },
        {
            "duration": 0.10000000149011612,
            "h": 23,
            "w": 18,
            "x": 90,
            "y": 58
        },
        {
            "duration": 0.10000000149011612,
            "h": 22,
            "w": 15,
            "x": 109,
            "y": 57
        },
        {
            "duration": 0.10000000149011612,
            "h": 23,
            "w": 16,
            "x": 126,
            "y": 57
        }
    ],
    "loop": true,
    "name": "Link_right"
}